vcparceiro/__init__.py
vcparceiro/resources.py
vcparceiro/subsystem/__init__.py
vcparceiro/subsystem/parceiro/__init__.py
vcparceiro/subsystem/parceiro/resource.py
vcparceiro/tests/__init__.py
vcparceiro/tests/functional/__init__.py
vcparceiro/tests/functional/fixtures.py
vcparceiro-1.1.3.dist-info/AUTHORS
vcparceiro-1.1.3.dist-info/METADATA
vcparceiro-1.1.3.dist-info/WHEEL
vcparceiro-1.1.3.dist-info/top_level.txt
vcparceiro-1.1.3.dist-info/RECORD
